Workbook
Name Aporte_inicial_formula: 'Dados de Entrada'!$D$27
Name Dividendo_mensal_por_cota: 'Dados de Entrada'!$D$21
Name nome_FII: 'Dados de Entrada'!$D$19
Name Preço_da_cota: 'Dados de Entrada'!$D$20
Name quantidade_de_cotas: 'Dados de Entrada'!$D$26

Sheet Dados de Entrada
C18: Informações do FII
C19: Nome do FII (opcional) | D19: FII 25625
C20: Preço da Cota (R$) | D20: 10
C21: Dividendo Mensal por Cota (R$) | D21: 0.7
C22: Frequencia de Pagamento | D22: Mensal
C25: Investimento Inicial
C26: Quantidade de Cotas | D26: 500
C27: Aporte Inicial (R$) | D27: =D20*D26 -> 5000
C30: Aportes Mensais
C31: Aporte Mensal (R$) | D31: 500
C32: Numero de Meses da Simulação | D32: 12
C33: Reinvestir Dividendos? (SIM ou Não) | D33: SIM
C36: Indicadores Principais
C37: Renda Mensal Estimada (R$) | D37: ='Dados de Entrada'!D26*'Dados de Entrada'!D21 -> 350
C38: Renda Anual Estimada (R$) | D38: =D37*12 -> 4200
C39: Dividend Yield Mensal (%) | D39: ='Dados de Entrada'!D21/'Dados de Entrada'!D20 -> 0.07
C40: Dividend Yield Anual (%) | D40: =D39*12 -> 0.84
C41: Total Investido (R$) | D41: ='Evolução do Investimento'!D18 -> 6000
C42: Total Recebido em Dividendos | D42: ='Evolução do Investimento'!F18 -> 2994.3133
C43: Quantidade Final de Cotas | D43: ='Evolução do Investimento'!E18 -> 600

Sheet Evolução do Investimento
B3: Evolução do Investimento
B5: Mês | C5: Cotas Iniciais | D5: Aporte (R$) | E5: Novas Cotas | F5: Dividendos (R$) | G5: Reinvestimento | H5: Cotas Finais
B6: 1 | C6: 4 | D6: ='Dados de Entrada'!D$31 -> 500 | E6: ='Dados de Entrada'!D$31/'Dados de Entrada'!D$20 -> 50 | F6: =C6*'Dados de Entrada'!D$21 -> 2.8 | G6: =IF('Dados de Entrada'!D$33 = "SIM",'Evolução do Investimento'!F6/'Dados de Entrada'!D$20, 0) -> 0.28 | H6: =C6+E6+G6 -> 54.28
B7: 2 | C7: =H6 -> 54.28 | D7: ='Dados de Entrada'!D$31 -> 500 | E7: ='Dados de Entrada'!D$31/'Dados de Entrada'!D$20 -> 50 | F7: =C7*'Dados de Entrada'!D$21 -> 37.996 | G7: =IF('Dados de Entrada'!D$33 = "SIM",'Evolução do Investimento'!F7/'Dados de Entrada'!D$20, 0) -> 3.7996 | H7: =C7+E7+G7 -> 108.0796
B8: 3 | C8: =H7 -> 108.0796 | D8: ='Dados de Entrada'!D$31 -> 500 | E8: ='Dados de Entrada'!D$31/'Dados de Entrada'!D$20 -> 50 | F8: =C8*'Dados de Entrada'!D$21 -> 75.65572 | G8: =IF('Dados de Entrada'!D$33 = "SIM",'Evolução do Investimento'!F8/'Dados de Entrada'!D$20, 0) -> 7.565572 | H8: =C8+E8+G8 -> 165.64517
B9: 4 | C9: =H8 -> 165.64517 | D9: ='Dados de Entrada'!D$31 -> 500 | E9: ='Dados de Entrada'!D$31/'Dados de Entrada'!D$20 -> 50 | F9: =C9*'Dados de Entrada'!D$21 -> 115.95162 | G9: =IF('Dados de Entrada'!D$33 = "SIM",'Evolução do Investimento'!F9/'Dados de Entrada'!D$20, 0) -> 11.595162 | H9: =C9+E9+G9 -> 227.24033
B10: 5 | C10: =H9 -> 227.24033 | D10: ='Dados de Entrada'!D$31 -> 500 | E10: ='Dados de Entrada'!D$31/'Dados de Entrada'!D$20 -> 50 | F10: =C10*'Dados de Entrada'!D$21 -> 159.06823 | G10: =IF('Dados de Entrada'!D$33 = "SIM",'Evolução do Investimento'!F10/'Dados de Entrada'!D$20, 0) -> 15.906823 | H10: =C10+E10+G10 -> 293.14716
B11: 6 | C11: =H10 -> 293.14716 | D11: ='Dados de Entrada'!D$31 -> 500 | E11: ='Dados de Entrada'!D$31/'Dados de Entrada'!D$20 -> 50 | F11: =C11*'Dados de Entrada'!D$21 -> 205.20301 | G11: =IF('Dados de Entrada'!D$33 = "SIM",'Evolução do Investimento'!F11/'Dados de Entrada'!D$20, 0) -> 20.520301 | H11: =C11+E11+G11 -> 363.66746
B12: 7 | C12: =H11 -> 363.66746 | D12: ='Dados de Entrada'!D$31 -> 500 | E12: ='Dados de Entrada'!D$31/'Dados de Entrada'!D$20 -> 50 | F12: =C12*'Dados de Entrada'!D$21 -> 254.56722 | G12: =IF('Dados de Entrada'!D$33 = "SIM",'Evolução do Investimento'!F12/'Dados de Entrada'!D$20, 0) -> 25.456722 | H12: =C12+E12+G12 -> 439.12418
B13: 8 | C13: =H12 -> 439.12418 | D13: ='Dados de Entrada'!D$31 -> 500 | E13: ='Dados de Entrada'!D$31/'Dados de Entrada'!D$20 -> 50 | F13: =C13*'Dados de Entrada'!D$21 -> 307.38693 | G13: =IF('Dados de Entrada'!D$33 = "SIM",'Evolução do Investimento'!F13/'Dados de Entrada'!D$20, 0) -> 30.738693 | H13: =C13+E13+G13 -> 519.86287
B14: 9 | C14: =H13 -> 519.86287 | D14: ='Dados de Entrada'!D$31 -> 500 | E14: ='Dados de Entrada'!D$31/'Dados de Entrada'!D$20 -> 50 | F14: =C14*'Dados de Entrada'!D$21 -> 363.90401 | G14: =IF('Dados de Entrada'!D$33 = "SIM",'Evolução do Investimento'!F14/'Dados de Entrada'!D$20, 0) -> 36.390401 | H14: =C14+E14+G14 -> 606.25327
B15: 10 | C15: =H14 -> 606.25327 | D15: ='Dados de Entrada'!D$31 -> 500 | E15: ='Dados de Entrada'!D$31/'Dados de Entrada'!D$20 -> 50 | F15: =C15*'Dados de Entrada'!D$21 -> 424.37729 | G15: =IF('Dados de Entrada'!D$33 = "SIM",'Evolução do Investimento'!F15/'Dados de Entrada'!D$20, 0) -> 42.437729 | H15: =C15+E15+G15 -> 698.691
B16: 11 | C16: =H15 -> 698.691 | D16: ='Dados de Entrada'!D$31 -> 500 | E16: ='Dados de Entrada'!D$31/'Dados de Entrada'!D$20 -> 50 | F16: =C16*'Dados de Entrada'!D$21 -> 489.0837 | G16: =IF('Dados de Entrada'!D$33 = "SIM",'Evolução do Investimento'!F16/'Dados de Entrada'!D$20, 0) -> 48.90837 | H16: =C16+E16+G16 -> 797.59937
B17: 12 | C17: =H16 -> 797.59937 | D17: ='Dados de Entrada'!D$31 -> 500 | E17: ='Dados de Entrada'!D$31/'Dados de Entrada'!D$20 -> 50 | F17: =C17*'Dados de Entrada'!D$21 -> 558.31956 | G17: =IF('Dados de Entrada'!D$33 = "SIM",'Evolução do Investimento'!F17/'Dados de Entrada'!D$20, 0) -> 55.831956 | H17: =C17+E17+G17 -> 903.43133
D18: =SUM(D6:D17) -> 6000 | E18: =SUM(E6:E17) -> 600 | F18: =SUM(F6:F17) -> 2994.3133

Sheet Perguntas de Negócio
B14: Perguntas de negócio:
B15: Qual o valor total investido?
B16: Qual o patrimônio acumulado?
B17: Quais são os dividendos mensais?
